teamai/__init__.py
teamai/agent.py
teamai/agents/__init__.py
teamai/agents/cache/__init__.py
teamai/agents/cache/cache_handler.py
teamai/agents/executor.py
teamai/agents/parser.py
teamai/agents/tools_handler.py
teamai/cli/__init__.py
teamai/cli/cli.py
teamai/cli/create_team.py
teamai/cli/templates/.gitignore
teamai/cli/templates/__init__.py
teamai/cli/templates/config/agents.yaml
teamai/cli/templates/config/tasks.yaml
teamai/cli/templates/main.py
teamai/cli/templates/pyproject.toml
teamai/cli/templates/README.md
teamai/cli/templates/team.py
teamai/cli/templates/tools/__init__.py
teamai/cli/templates/tools/custom_tool.py
teamai/memory/__init__.py
teamai/memory/contextual/__init__.py
teamai/memory/contextual/contextual_memory.py
teamai/memory/entity/__init__.py
teamai/memory/entity/entity_memory.py
teamai/memory/entity/entity_memory_item.py
teamai/memory/long_term/__init__.py
teamai/memory/long_term/long_term_memory.py
teamai/memory/long_term/long_term_memory_item.py
teamai/memory/memory.py
teamai/memory/short_term/__init__.py
teamai/memory/short_term/short_term_memory.py
teamai/memory/short_term/short_term_memory_item.py
teamai/memory/storage/interface.py
teamai/memory/storage/ltm_sqlite_storage.py
teamai/memory/storage/rag_storage.py
teamai/process.py
teamai/project/__init__.py
teamai/project/annotations.py
teamai/project/team_base.py
teamai/task.py
teamai/tasks/__init__.py
teamai/tasks/task_output.py
teamai/team.py
teamai/telemetry/__init__.py
teamai/telemetry/telemetry.py
teamai/tools/__init__.py
teamai/tools/agent_tools.py
teamai/tools/cache_tools.py
teamai/tools/tool_calling.py
teamai/tools/tool_output_parser.py
teamai/tools/tool_usage.py
teamai/translations/en.json
teamai/utilities/__init__.py
teamai/utilities/converter.py
teamai/utilities/evaluators/task_evaluator.py
teamai/utilities/fileHandler.py
teamai/utilities/i18n.py
teamai/utilities/instructor.py
teamai/utilities/logger.py
teamai/utilities/paths.py
teamai/utilities/printer.py
teamai-0.30.0rc5.dist-info/entry_points.txt
teamai-0.30.0rc5.dist-info/LICENSE
teamai-0.30.0rc5.dist-info/METADATA
teamai-0.30.0rc5.dist-info/WHEEL
teamai-0.30.0rc5.dist-info/RECORD
