Metadata-Version: 2.1
Name: teamai
Version: 0.30.0rc5
Summary: Cutting-edge framework for orchestrating role-playing, autonomous AI agents. By fostering collaborative intelligence, TeamAI empowers agents to work together seamlessly, tackling complex tasks.
Author: DCL
Author-email: dcl@teamai.dev
Requires-Python: >=3.10,<=3.13
Classifier: Programming Language :: Python :: 3
Classifier: Programming Language :: Python :: 3.10
Classifier: Programming Language :: Python :: 3.11
Classifier: Programming Language :: Python :: 3.12
Provides-Extra: tools
Requires-Dist: agentops (==0.1.6)
Requires-Dist: appdirs (>=1.4.4,<2.0.0)
Requires-Dist: click (>=8.1.7,<9.0.0)
Requires-Dist: embedchain (>=0.1.98,<0.2.0)
Requires-Dist: instructor (>=0.5.2,<0.6.0)
Requires-Dist: langchain (>=0.1.10,<0.2.0)
Requires-Dist: openai (>=1.13.3,<2.0.0)
Requires-Dist: opentelemetry-api (>=1.22.0,<2.0.0)
Requires-Dist: opentelemetry-exporter-otlp-proto-http (>=1.22.0,<2.0.0)
Requires-Dist: opentelemetry-sdk (>=1.22.0,<2.0.0)
Requires-Dist: pydantic (>=2.4.2,<3.0.0)
Requires-Dist: python-dotenv (>=1.0.0,<2.0.0)
Requires-Dist: regex (>=2023.12.25,<2024.0.0)
Requires-Dist: teamai-tools (>=0.2.3,<0.3.0) ; extra == "tools"
Project-URL: Documentation, https://github.com/Decentralized-Labs-Inc/TeamAI/wiki/Index
Project-URL: Homepage, https://teamai.dev
Project-URL: Repository, https://github.com/Decentralized-Labs-Inc/teamai
